micropython_qmc5883l/__init__.py
micropython_qmc5883l/i2c_helpers.py
micropython_qmc5883l/qmc5883l.py
micropython_qmc5883l-0.1.2.dist-info/LICENSE
micropython_qmc5883l-0.1.2.dist-info/METADATA
micropython_qmc5883l-0.1.2.dist-info/WHEEL
micropython_qmc5883l-0.1.2.dist-info/top_level.txt
micropython_qmc5883l-0.1.2.dist-info/RECORD
