Metadata-Version: 2.1
Name: micropython-qmc5883l
Version: 0.1.2
Summary: MicroPython Driver for the QMC5883L Accelerometer
Author-email: JDM <xxyx@mailmeto.mozmail.com>
License: MIT
Project-URL: Homepage, https://github.com/jposada202020/MicroPython_QMC5883L
Keywords: sensor,micropython,qmc5883l,acceleration,heading,driver,gravity,accelerometer
Classifier: Intended Audience :: Developers
Classifier: Topic :: Software Development :: Libraries
Classifier: Topic :: Software Development :: Embedded Systems
Classifier: Topic :: System :: Hardware
Classifier: License :: OSI Approved :: MIT License
Classifier: Programming Language :: Python :: Implementation :: MicroPython
License-File: LICENSE
